varphi_parsing_tools/VarphiLexer.py
varphi_parsing_tools/VarphiListener.py
varphi_parsing_tools/VarphiParser.py
varphi_parsing_tools/VarphiRepresentor.py
varphi_parsing_tools/VarphiSyntaxErrorListener.py
varphi_parsing_tools/__init__.py
varphi_parsing_tools-0.0.4.dist-info/LICENSE
varphi_parsing_tools-0.0.4.dist-info/METADATA
varphi_parsing_tools-0.0.4.dist-info/WHEEL
varphi_parsing_tools-0.0.4.dist-info/top_level.txt
varphi_parsing_tools-0.0.4.dist-info/RECORD
