Metadata-Version: 2.1
Name: varphi_parsing_tools
Version: 0.0.4
Summary: Lexer, parser, and representor for the Varphi programming language.
Home-page: https://github.com/hassanelsheikha/varphi_parsing_tools
Author: Hassan El-Sheikha
Author-email: hassan.elsheikha@utoronto.ca
Classifier: Programming Language :: Python :: 3
Classifier: License :: OSI Approved :: BSD License
Classifier: Operating System :: OS Independent
License-File: LICENSE
Requires-Dist: antlr4-python3-runtime==4.13.2
Requires-Dist: varphi_types==0.0.4
